simple_scenario/__init__.py
simple_scenario/_check_extra_availability.py
simple_scenario/cli.py
simple_scenario/ego_configuration.py
simple_scenario/from_data_config_error.py
simple_scenario/scenario.py
simple_scenario/vehicle.py
simple_scenario/commonroad_interface/__init__.py
simple_scenario/commonroad_interface/commonroad_interface.py
simple_scenario/commonroad_interface/lanelet_network_creator.py
simple_scenario/commonroad_interface/traffic_sign_fixed.py
simple_scenario/lanelet_network_wrapper/__init__.py
simple_scenario/lanelet_network_wrapper/lanelet_network_wrapper.py
simple_scenario/lanelet_network_wrapper/neighbour_lanes.py
simple_scenario/lanelet_network_wrapper/out_of_projection_domain_exception.py
simple_scenario/lanelet_network_wrapper/surrounding_vehicles.py
simple_scenario/lanelet_network_wrapper/traffic_sign_interpreter_fixed.py
simple_scenario/lxd/__init__.py
simple_scenario/lxd/highd_extractor.py
simple_scenario/rendering/__init__.py
simple_scenario/rendering/renderable.py
simple_scenario/rendering/scenario_plot_context_manager.py
simple_scenario/road/__init__.py
simple_scenario/road/arc_segment.py
simple_scenario/road/clothoid_segment.py
simple_scenario/road/polyline_segment.py
simple_scenario/road/road.py
simple_scenario/road/road_segment.py
simple_scenario/road/straight_segment.py
simple_scenario-0.10.1.dist-info/LICENSE
simple_scenario-0.10.1.dist-info/METADATA
simple_scenario-0.10.1.dist-info/WHEEL
simple_scenario-0.10.1.dist-info/entry_points.txt
simple_scenario-0.10.1.dist-info/top_level.txt
simple_scenario-0.10.1.dist-info/RECORD
