Metadata-Version: 2.1
Name: simple_scenario
Version: 0.10.1
Summary: Quickly generate prototype test scenarios for automated driving
Author-email: Lennart Vater <lennart.vater@ika.rwth-aachen.de>
Maintainer-email: Lennart Vater <lennart.vater@ika.rwth-aachen.de>
License: MIT
Classifier: Development Status :: 4 - Beta
Classifier: Intended Audience :: Science/Research
Classifier: License :: OSI Approved :: MIT License
Classifier: Programming Language :: Python
Classifier: Topic :: Scientific/Engineering
Requires-Python: >=3.8
License-File: LICENSE
Requires-Dist: commonroad-vehicle-models ==3.0.2
Requires-Dist: lanelet2 >=1.2.2
Requires-Dist: loguru >=0.7.3
Requires-Dist: matplotlib >=3.7.5
Requires-Dist: numpy >=1.24.4
Requires-Dist: pillow >=10.4.0
Requires-Dist: pyclothoids >=0.1.5
Requires-Dist: scenariogeneration >=0.14.9
Requires-Dist: typer >=0.15.2
Provides-Extra: commonroad
Requires-Dist: commonroad-drivability-checker ==2022.1 ; extra == 'commonroad'
Requires-Dist: commonroad-io ==2022.1 ; extra == 'commonroad'
Requires-Dist: shapely ==1.8.5.post1 ; extra == 'commonroad'
Provides-Extra: lxd
Requires-Dist: lxd-io >=0.4.5 ; extra == 'lxd'
